edc_visit_tracking/__init__.py
edc_visit_tracking/action_items.py
edc_visit_tracking/admin.py
edc_visit_tracking/admin_site.py
edc_visit_tracking/apps.py
edc_visit_tracking/choices.py
edc_visit_tracking/constants.py
edc_visit_tracking/context_processors.py
edc_visit_tracking/crf_date_validator.py
edc_visit_tracking/exceptions.py
edc_visit_tracking/form_validators/__init__.py
edc_visit_tracking/form_validators/visit_form_validator.py
edc_visit_tracking/form_validators/visit_missed_form_validator.py
edc_visit_tracking/locale/sw/LC_MESSAGES/django.mo
edc_visit_tracking/locale/sw/LC_MESSAGES/django.po
edc_visit_tracking/managers.py
edc_visit_tracking/migrations/0001_initial.py
edc_visit_tracking/migrations/0002_auto_20210423_1451.py
edc_visit_tracking/migrations/0003_auto_20220913_2139.py
edc_visit_tracking/migrations/0004_subjectvisit_subjectvisitmissedreasons_extra_value_and_more.py
edc_visit_tracking/migrations/0005_alter_subjectvisit_options_and_more.py
edc_visit_tracking/migrations/0006_alter_historicalsubjectvisit_site_and_more.py
edc_visit_tracking/migrations/0007_alter_historicalsubjectvisit_consent_model_and_more.py
edc_visit_tracking/migrations/__init__.py
edc_visit_tracking/model_mixins/__init__.py
edc_visit_tracking/model_mixins/base/__init__.py
edc_visit_tracking/model_mixins/base/visit_methods_model_mixin.py
edc_visit_tracking/model_mixins/crfs/__init__.py
edc_visit_tracking/model_mixins/crfs/inline_visits_methods_model_mixin.py
edc_visit_tracking/model_mixins/crfs/visit_tracking_crf_model_mixin.py
edc_visit_tracking/model_mixins/requisitions/__init__.py
edc_visit_tracking/model_mixins/requisitions/visit_tracking_requisition_model_mixin.py
edc_visit_tracking/model_mixins/subject_visit_missed_model_mixin.py
edc_visit_tracking/model_mixins/utils.py
edc_visit_tracking/model_mixins/visit_model_mixin/__init__.py
edc_visit_tracking/model_mixins/visit_model_mixin/caretaker_fields_mixin.py
edc_visit_tracking-1.0.6.dist-info/licenses/LICENSE
edc_visit_tracking-1.0.6.dist-info/WHEEL
edc_visit_tracking-1.0.6.dist-info/METADATA
edc_visit_tracking-1.0.6.dist-info/RECORD
